luminanet/__init__.py
luminanet/core/__init__.py
luminanet/core/activations.py
luminanet/core/constraints.py
luminanet/core/initializers.py
luminanet/core/layers.py
luminanet/core/regulizers.py
luminanet/examples/__init__.py
luminanet/examples/basic_usage.py
luminanet/layers/__init__.py
luminanet/layers/advanced.py
luminanet/layers/convolutional.py
luminanet/layers/recurrent.py
luminanet/losses/__init__.py
luminanet/losses/loss_functions.py
luminanet/models/__init__.py
luminanet/models/model.py
luminanet/optimizers/__init__.py
luminanet/optimizers/adam.py
luminanet/optimizers/base.py
luminanet/optimizers/rmsprop.py
luminanet/optimizers/sgd.py
luminanet/text/__init__.py
luminanet/text/processing.py
luminanet/utils/__init__.py
luminanet/utils/callbacks.py
luminanet-1.0.0.dist-info/licenses/LICENSE
luminanet-1.0.0.dist-info/METADATA
luminanet-1.0.0.dist-info/WHEEL
luminanet-1.0.0.dist-info/top_level.txt
luminanet-1.0.0.dist-info/RECORD
