Metadata-Version: 2.4
Name: luminanet
Version: 1.0.0
Summary: LuminaNet: Pure Python Deep Learning Framework - Illuminate AI with Minimal Dependencies
Author: Your Name
Author-email: your.email@example.com
Project-URL: Source, https://github.com/iyazkasep/luminanet
Project-URL: Bug Reports, https://github.com/iyazkasep/luminanet/issues
Keywords: deep learning,neural networks,machine learning,pure python,termux,numpy,educational,luminanet
Classifier: Development Status :: 4 - Beta
Classifier: Intended Audience :: Education
Classifier: Intended Audience :: Science/Research
Classifier: License :: OSI Approved :: MIT License
Classifier: Programming Language :: Python :: 3
Classifier: Programming Language :: Python :: 3.7
Classifier: Programming Language :: Python :: 3.8
Classifier: Programming Language :: Python :: 3.9
Classifier: Programming Language :: Python :: 3.10
Classifier: Topic :: Scientific/Engineering :: Artificial Intelligence
Classifier: Topic :: Education
Requires-Python: >=3.7
License-File: LICENSE
Requires-Dist: numpy>=1.21.0
Requires-Dist: scipy>=1.7.0
Requires-Dist: nltk>=3.6.0
Requires-Dist: sastrawi>=1.0.0
Dynamic: author
Dynamic: author-email
Dynamic: classifier
Dynamic: description
Dynamic: description-content-type
Dynamic: keywords
Dynamic: license-file
Dynamic: project-url
Dynamic: requires-dist
Dynamic: requires-python
Dynamic: summary
